tinymongo/serializers.py
tinymongo/results.py
tinymongo/__init__.py
tinymongo/errors.py
tinymongo/tinymongo.py
tinymongo-0.2.0.dist-info/WHEEL
tinymongo-0.2.0.dist-info/RECORD
tinymongo-0.2.0.dist-info/METADATA
tinymongo-0.2.0.dist-info/DESCRIPTION.rst
tinymongo-0.2.0.dist-info/top_level.txt
tinymongo-0.2.0.dist-info/metadata.json
