Metadata-Version: 2.0
Name: tinymongo
Version: 0.2.0
Summary: A flat file drop in replacement for mongodb.  Requires Tinydb
Home-page: https://github.com/schapman1974/tinymongo
Author: Stephen Chapman, Jason Jones
Author-email: schapman1974@gmail.com
License: UNKNOWN
Download-URL: https://github.com/schapman1974/tinymongo/archive/master.zip
Keywords: mongodb,drop-in,database,tinydb
Platform: UNKNOWN
Classifier: Programming Language :: Python :: 2.7
Classifier: Programming Language :: Python :: 3.3
Classifier: Programming Language :: Python :: 3.4
Classifier: Programming Language :: Python :: 3.5
Classifier: Programming Language :: Python :: 3.6
Requires-Dist: tinydb (>=3.2.1)
Requires-Dist: tinydb-serialization (>=1.0.4)
